Metadata-Version: 2.1
Name: example-pkg-mahendran
Version: 0.2
Summary: A small example package
Home-page: UNKNOWN
Author: Mahendran
Author-email: mahendrannnm@gmail.com
License: UNKNOWN
Platform: UNKNOWN
Classifier: Programming Language :: Python :: 3
Classifier: License :: OSI Approved :: MIT License
Classifier: Operating System :: OS Independent
Requires-Python: >=3.6
Requires-Dist: imageio
